CTkKeyboard/__init__.py
CTkKeyboard/main.py
CTkKeyboard-0.3.6.dist-info/METADATA
CTkKeyboard-0.3.6.dist-info/WHEEL
CTkKeyboard-0.3.6.dist-info/top_level.txt
CTkKeyboard-0.3.6.dist-info/RECORD
