Metadata-Version: 2.1
Name: CTkKeyboard
Version: 0.3.6
Summary: A virtual keyboard for CustomTkinter, making it easy to enter text on a Raspberry Pi with a touch display.
Home-page: https://github.com/CadamTechnology/CTkKeyboard
Author: Cadam
Classifier: Programming Language :: Python :: 3
Classifier: License :: OSI Approved :: MIT License
Classifier: Operating System :: OS Independent
Requires-Python: >=3.6
Requires-Dist: customtkinter
